gtodo_sprokkel78/CHANGELOG
gtodo_sprokkel78/LICENSE
gtodo_sprokkel78/README.md
gtodo_sprokkel78/__init__
gtodo_sprokkel78/__init__.py
gtodo_sprokkel78/gtodo.css
gtodo_sprokkel78/gtodo.desktop
gtodo_sprokkel78/gtodo.png
gtodo_sprokkel78/gtodo.py
gtodo_sprokkel78/gtodo.svg
gtodo_sprokkel78/install.sh
gtodo_sprokkel78/uninstall.sh
gtodo_sprokkel78/screenshots/gTodo-1.png
gtodo_sprokkel78-1.0.4.dist-info/METADATA
gtodo_sprokkel78-1.0.4.dist-info/WHEEL
gtodo_sprokkel78-1.0.4.dist-info/licenses/LICENSE
gtodo_sprokkel78-1.0.4.dist-info/RECORD
